LICENSE
MANIFEST.in
README.md
pyproject.toml
setup.cfg
setup.py
rfind/__init__.py
rfind/cli.py
rfind.egg-info/PKG-INFO
rfind.egg-info/SOURCES.txt
rfind.egg-info/dependency_links.txt
rfind.egg-info/entry_points.txt
rfind.egg-info/not-zip-safe
rfind.egg-info/requires.txt
rfind.egg-info/top_level.txt
rfind/src/generator.c
rfind/src/rfindmodule.c
rfind/src/scanner.c
rfind/src/scanner.h
rfind/src/worker.c