Metadata-Version: 2.4
Name: rfind
Version: 0.4.0
Summary: ⚡ Ultra-fast file discovery in directories with execute-only permission - Pure C acceleration with Python wrapper
Home-page: https://github.com/nsyhykui/rfind
Author: nsyhykui
Author-email: nsyhykui <nsyhykui@outlook.com>
License: MIT
Keywords: security,enumeration,file-discovery,permission-bypass,pentesting,android,linux,forensics,c-extension,performance,multi-threading,parallel
Classifier: Development Status :: 4 - Beta
Classifier: Intended Audience :: Information Technology
Classifier: Intended Audience :: System Administrators
Classifier: Topic :: Security
Classifier: Topic :: System :: Systems Administration
Classifier: Topic :: System :: Shells
Classifier: Topic :: Utilities
Classifier: License :: OSI Approved :: MIT License
Classifier: Programming Language :: Python :: 3
Classifier: Programming Language :: Python :: 3.6
Classifier: Programming Language :: Python :: 3.7
Classifier: Programming Language :: Python :: 3.8
Classifier: Programming Language :: Python :: 3.9
Classifier: Programming Language :: Python :: 3.10
Classifier: Programming Language :: Python :: 3.11
Classifier: Programming Language :: Python :: 3.12
Classifier: Programming Language :: Python :: 3.13
Classifier: Programming Language :: C
Classifier: Operating System :: POSIX :: Linux
Classifier: Operating System :: Android
Classifier: Environment :: Console
Requires-Python: >=3.6
License-File: LICENSE
Provides-Extra: dev
Requires-Dist: build>=0.10.0; extra == "dev"
Requires-Dist: twine>=4.0.0; extra == "dev"
Requires-Dist: pytest>=7.0.0; extra == "dev"
Requires-Dist: coverage>=7.0.0; extra == "dev"
Provides-Extra: benchmark
Requires-Dist: psutil>=5.9.0; extra == "benchmark"
Requires-Dist: rich>=13.0.0; extra == "benchmark"
Dynamic: author
Dynamic: home-page
Dynamic: license-file
Dynamic: requires-python
